{
  "updated": 1764140483199,
  "data": {
    "GOLD : 1 KILO 999.9 (MYR)": {
      "buy": 549440,
      "sell": 552864
    },
    "GOLD : 100 GM 999.9 (MYR)": {
      "buy": 54947,
      "sell": 55330
    },
    "GOLD : 50 GM 999.9 (MYR)": {
      "buy": 27474,
      "sell": 27678
    },
    "GOLD : 1 TAEL 999.9 (MYR)": {
      "buy": 20765,
      "sell": 20894
    },
    "SCRAP GOLD IN FINE WEIGHT OF 1KG": {
      "buy": 548777,
      "sell": null
    },
    "SILVER : 1 GRAM 999.0 (MYR)": {
      "buy": 6.47,
      "sell": 7.39
    },
    "GOLD OZ": {
      "buy": 4148.56,
      "sell": 4150.78
    },
    "SILVER OZ": {
      "buy": 51.82,
      "sell": 52.05
    },
    "USD/MYR": {
      "buy": 4.1247,
      "sell": 4.1397
    }
  }
}