{
  "updated": 1761323911932,
  "data": {
    "GOLD : 1 KILO 999.9 (MYR)": {
      "buy": 558567,
      "sell": 563402
    },
    "GOLD : 100 GM 999.9 (MYR)": {
      "buy": 55860,
      "sell": 56385
    },
    "GOLD : 50 GM 999.9 (MYR)": {
      "buy": 27930,
      "sell": 28206
    },
    "GOLD : 1 TAEL 999.9 (MYR)": {
      "buy": 21110,
      "sell": 21293
    },
    "SCRAP GOLD IN FINE WEIGHT OF 1KG": {
      "buy": 557891,
      "sell": null
    },
    "SILVER : 1 GRAM 999.0 (MYR)": {
      "buy": 6.18,
      "sell": 7.13
    },
    "GOLD OZ": {
      "buy": 4132.93,
      "sell": 4134.79
    },
    "SILVER OZ": {
      "buy": 48.67,
      "sell": 48.89
    },
    "USD/MYR": {
      "buy": 4.2091,
      "sell": 4.2349
    }
  }
}