{
  "updated": 1762155524287,
  "data": {
    "GOLD : 1 KILO 999.9 (MYR)": {
      "buy": 540899,
      "sell": 544248
    },
    "GOLD : 100 GM 999.9 (MYR)": {
      "buy": 54093,
      "sell": 54469
    },
    "GOLD : 50 GM 999.9 (MYR)": {
      "buy": 27047,
      "sell": 27248
    },
    "GOLD : 1 TAEL 999.9 (MYR)": {
      "buy": 20442,
      "sell": 20569
    },
    "SCRAP GOLD IN FINE WEIGHT OF 1KG": {
      "buy": 540226,
      "sell": null
    },
    "SILVER : 1 GRAM 999.0 (MYR)": {
      "buy": 6.19,
      "sell": 7.12
    },
    "GOLD OZ": {
      "buy": 4021.54,
      "sell": 4023.49
    },
    "SILVER OZ": {
      "buy": 48.93,
      "sell": 49.15
    },
    "USD/MYR": {
      "buy": 4.189,
      "sell": 4.204
    }
  }
}