{
  "updated": 1763484318039,
  "data": {
    "GOLD : 1 KILO 999.9 (MYR)": {
      "buy": 540921,
      "sell": 545783
    },
    "GOLD : 100 GM 999.9 (MYR)": {
      "buy": 54095,
      "sell": 54622
    },
    "GOLD : 50 GM 999.9 (MYR)": {
      "buy": 27048,
      "sell": 27324
    },
    "GOLD : 1 TAEL 999.9 (MYR)": {
      "buy": 20443,
      "sell": 20627
    },
    "SCRAP GOLD IN FINE WEIGHT OF 1KG": {
      "buy": 540254,
      "sell": null
    },
    "SILVER : 1 GRAM 999.0 (MYR)": {
      "buy": 6.35,
      "sell": 7.29
    },
    "GOLD OZ": {
      "buy": 4061.6,
      "sell": 4063.58
    },
    "SILVER OZ": {
      "buy": 50.59,
      "sell": 50.81
    },
    "USD/MYR": {
      "buy": 4.1478,
      "sell": 4.1743
    }
  }
}