{
  "updated": 1763393242002,
  "data": {
    "GOLD : 1 KILO 999.9 (MYR)": {
      "buy": 540096,
      "sell": 544965
    },
    "GOLD : 100 GM 999.9 (MYR)": {
      "buy": 54013,
      "sell": 54540
    },
    "GOLD : 50 GM 999.9 (MYR)": {
      "buy": 27007,
      "sell": 27283
    },
    "GOLD : 1 TAEL 999.9 (MYR)": {
      "buy": 20412,
      "sell": 20596
    },
    "SCRAP GOLD IN FINE WEIGHT OF 1KG": {
      "buy": 539432,
      "sell": null
    },
    "SILVER : 1 GRAM 999.0 (MYR)": {
      "buy": 6.33,
      "sell": 7.27
    },
    "GOLD OZ": {
      "buy": 4068.15,
      "sell": 4070.17
    },
    "SILVER OZ": {
      "buy": 50.64,
      "sell": 50.87
    },
    "USD/MYR": {
      "buy": 4.1348,
      "sell": 4.1613
    }
  }
}