{
  "updated": 1763572924671,
  "data": {
    "GOLD : 1 KILO 999.9 (MYR)": {
      "buy": 540047,
      "sell": 544914
    },
    "GOLD : 100 GM 999.9 (MYR)": {
      "buy": 54008,
      "sell": 54535
    },
    "GOLD : 50 GM 999.9 (MYR)": {
      "buy": 27004,
      "sell": 27281
    },
    "GOLD : 1 TAEL 999.9 (MYR)": {
      "buy": 20410,
      "sell": 20594
    },
    "SCRAP GOLD IN FINE WEIGHT OF 1KG": {
      "buy": 539383,
      "sell": null
    },
    "SILVER : 1 GRAM 999.0 (MYR)": {
      "buy": 6.33,
      "sell": 7.28
    },
    "GOLD OZ": {
      "buy": 4067.78,
      "sell": 4069.79
    },
    "SILVER OZ": {
      "buy": 50.64,
      "sell": 50.88
    },
    "USD/MYR": {
      "buy": 4.1348,
      "sell": 4.1613
    }
  }
}