{
  "updated": 1762369033803,
  "data": {
    "GOLD : 1 KILO 999.9 (MYR)": {
      "buy": 533615,
      "sell": 538439
    },
    "GOLD : 100 GM 999.9 (MYR)": {
      "buy": 53365,
      "sell": 53888
    },
    "GOLD : 50 GM 999.9 (MYR)": {
      "buy": 26682,
      "sell": 26957
    },
    "GOLD : 1 TAEL 999.9 (MYR)": {
      "buy": 20167,
      "sell": 20349
    },
    "SCRAP GOLD IN FINE WEIGHT OF 1KG": {
      "buy": 532944,
      "sell": null
    },
    "SILVER : 1 GRAM 999.0 (MYR)": {
      "buy": 6.05,
      "sell": 6.99
    },
    "GOLD OZ": {
      "buy": 3981.02,
      "sell": 3982.97
    },
    "SILVER OZ": {
      "buy": 48.05,
      "sell": 48.28
    },
    "USD/MYR": {
      "buy": 4.1747,
      "sell": 4.2014
    }
  }
}