{
  "updated": 1762405230155,
  "data": {
    "GOLD : 1 KILO 999.9 (MYR)": {
      "buy": 534042,
      "sell": 537385
    },
    "GOLD : 100 GM 999.9 (MYR)": {
      "buy": 53407,
      "sell": 53782
    },
    "GOLD : 50 GM 999.9 (MYR)": {
      "buy": 26704,
      "sell": 26905
    },
    "GOLD : 1 TAEL 999.9 (MYR)": {
      "buy": 20183,
      "sell": 20309
    },
    "SCRAP GOLD IN FINE WEIGHT OF 1KG": {
      "buy": 533371,
      "sell": null
    },
    "SILVER : 1 GRAM 999.0 (MYR)": {
      "buy": 6.06,
      "sell": 6.98
    },
    "GOLD OZ": {
      "buy": 3987.54,
      "sell": 3989.61
    },
    "SILVER OZ": {
      "buy": 48.16,
      "sell": 48.39
    },
    "USD/MYR": {
      "buy": 4.1712,
      "sell": 4.1862
    }
  }
}