{
  "updated": 1765819125198,
  "data": {
    "GOLD : 1 KILO 999.9 (MYR)": {
      "buy": 562312,
      "sell": 567224
    },
    "GOLD : 100 GM 999.9 (MYR)": {
      "buy": 56235,
      "sell": 56765
    },
    "GOLD : 50 GM 999.9 (MYR)": {
      "buy": 28117,
      "sell": 28396
    },
    "GOLD : 1 TAEL 999.9 (MYR)": {
      "buy": 21251,
      "sell": 21437
    },
    "SCRAP GOLD IN FINE WEIGHT OF 1KG": {
      "buy": 561657,
      "sell": null
    },
    "SILVER : 1 GRAM 999.0 (MYR)": {
      "buy": 7.9,
      "sell": 8.75
    },
    "GOLD OZ": {
      "buy": 4293.57,
      "sell": 4295.44
    },
    "SILVER OZ": {
      "buy": 63.26,
      "sell": 63.49
    },
    "USD/MYR": {
      "buy": 4.0786,
      "sell": 4.1043
    }
  }
}