{
  "updated": 1766370596124,
  "data": {
    "GOLD : 1 KILO 999.9 (MYR)": {
      "buy": 571501,
      "sell": 575142
    },
    "GOLD : 100 GM 999.9 (MYR)": {
      "buy": 57154,
      "sell": 57557
    },
    "GOLD : 50 GM 999.9 (MYR)": {
      "buy": 28577,
      "sell": 28792
    },
    "GOLD : 1 TAEL 999.9 (MYR)": {
      "buy": 21599,
      "sell": 21736
    },
    "SCRAP GOLD IN FINE WEIGHT OF 1KG": {
      "buy": 570848,
      "sell": null
    },
    "SILVER : 1 GRAM 999.0 (MYR)": {
      "buy": 8.54,
      "sell": 9.37
    },
    "GOLD OZ": {
      "buy": 4378.45,
      "sell": 4380.55
    },
    "SILVER OZ": {
      "buy": 68.37,
      "sell": 68.61
    },
    "USD/MYR": {
      "buy": 4.0648,
      "sell": 4.0808
    }
  }
}