{
  "updated": 1763415013732,
  "data": {
    "GOLD : 1 KILO 999.9 (MYR)": {
      "buy": 536700,
      "sell": 541582
    },
    "GOLD : 100 GM 999.9 (MYR)": {
      "buy": 53673,
      "sell": 54202
    },
    "GOLD : 50 GM 999.9 (MYR)": {
      "buy": 26837,
      "sell": 27114
    },
    "GOLD : 1 TAEL 999.9 (MYR)": {
      "buy": 20284,
      "sell": 20468
    },
    "SCRAP GOLD IN FINE WEIGHT OF 1KG": {
      "buy": 536036,
      "sell": null
    },
    "SILVER : 1 GRAM 999.0 (MYR)": {
      "buy": 6.25,
      "sell": 7.2
    },
    "GOLD OZ": {
      "buy": 4042.6,
      "sell": 4044.88
    },
    "SILVER OZ": {
      "buy": 50.05,
      "sell": 50.29
    },
    "USD/MYR": {
      "buy": 4.1348,
      "sell": 4.1613
    }
  }
}