{
  "updated": 1763585021062,
  "data": {
    "GOLD : 1 KILO 999.9 (MYR)": {
      "buy": 541044,
      "sell": 545947
    },
    "GOLD : 100 GM 999.9 (MYR)": {
      "buy": 54108,
      "sell": 54638
    },
    "GOLD : 50 GM 999.9 (MYR)": {
      "buy": 27054,
      "sell": 27333
    },
    "GOLD : 1 TAEL 999.9 (MYR)": {
      "buy": 20448,
      "sell": 20633
    },
    "SCRAP GOLD IN FINE WEIGHT OF 1KG": {
      "buy": 540380,
      "sell": null
    },
    "SILVER : 1 GRAM 999.0 (MYR)": {
      "buy": 6.4,
      "sell": 7.34
    },
    "GOLD OZ": {
      "buy": 4075.28,
      "sell": 4077.51
    },
    "SILVER OZ": {
      "buy": 51.11,
      "sell": 51.34
    },
    "USD/MYR": {
      "buy": 4.1348,
      "sell": 4.1613
    }
  }
}