{
  "updated": 1762771200968,
  "data": {
    "GOLD : 1 KILO 999.9 (MYR)": {
      "buy": 542897,
      "sell": 547759
    },
    "GOLD : 100 GM 999.9 (MYR)": {
      "buy": 54293,
      "sell": 54820
    },
    "GOLD : 50 GM 999.9 (MYR)": {
      "buy": 27147,
      "sell": 27423
    },
    "GOLD : 1 TAEL 999.9 (MYR)": {
      "buy": 20518,
      "sell": 20701
    },
    "SCRAP GOLD IN FINE WEIGHT OF 1KG": {
      "buy": 542231,
      "sell": null
    },
    "SILVER : 1 GRAM 999.0 (MYR)": {
      "buy": 6.24,
      "sell": 7.18
    },
    "GOLD OZ": {
      "buy": 4081.33,
      "sell": 4083.2
    },
    "SILVER OZ": {
      "buy": 49.83,
      "sell": 50.05
    },
    "USD/MYR": {
      "buy": 4.1428,
      "sell": 4.1693
    }
  }
}