{
  "updated": 1762353365022,
  "data": {
    "GOLD : 1 KILO 999.9 (MYR)": {
      "buy": 533605,
      "sell": 538443
    },
    "GOLD : 100 GM 999.9 (MYR)": {
      "buy": 53364,
      "sell": 53888
    },
    "GOLD : 50 GM 999.9 (MYR)": {
      "buy": 26682,
      "sell": 26958
    },
    "GOLD : 1 TAEL 999.9 (MYR)": {
      "buy": 20167,
      "sell": 20349
    },
    "SCRAP GOLD IN FINE WEIGHT OF 1KG": {
      "buy": 532934,
      "sell": null
    },
    "SILVER : 1 GRAM 999.0 (MYR)": {
      "buy": 6.02,
      "sell": 6.97
    },
    "GOLD OZ": {
      "buy": 3980.95,
      "sell": 3983
    },
    "SILVER OZ": {
      "buy": 47.84,
      "sell": 48.08
    },
    "USD/MYR": {
      "buy": 4.1747,
      "sell": 4.2014
    }
  }
}