{
  "updated": 1761325312786,
  "data": {
    "GOLD : 1 KILO 999.9 (MYR)": {
      "buy": 558563,
      "sell": 563393
    },
    "GOLD : 100 GM 999.9 (MYR)": {
      "buy": 55860,
      "sell": 56384
    },
    "GOLD : 50 GM 999.9 (MYR)": {
      "buy": 27930,
      "sell": 28205
    },
    "GOLD : 1 TAEL 999.9 (MYR)": {
      "buy": 21110,
      "sell": 21292
    },
    "SCRAP GOLD IN FINE WEIGHT OF 1KG": {
      "buy": 557887,
      "sell": null
    },
    "SILVER : 1 GRAM 999.0 (MYR)": {
      "buy": 6.19,
      "sell": 7.15
    },
    "GOLD OZ": {
      "buy": 4132.9,
      "sell": 4134.73
    },
    "SILVER OZ": {
      "buy": 48.75,
      "sell": 48.98
    },
    "USD/MYR": {
      "buy": 4.2091,
      "sell": 4.2349
    }
  }
}