{
  "updated": 1761914923720,
  "data": {
    "GOLD : 1 KILO 999.9 (MYR)": {
      "buy": 540971,
      "sell": 545340
    },
    "GOLD : 100 GM 999.9 (MYR)": {
      "buy": 54100,
      "sell": 54578
    },
    "GOLD : 50 GM 999.9 (MYR)": {
      "buy": 27050,
      "sell": 27302
    },
    "GOLD : 1 TAEL 999.9 (MYR)": {
      "buy": 20445,
      "sell": 20610
    },
    "SCRAP GOLD IN FINE WEIGHT OF 1KG": {
      "buy": 540299,
      "sell": null
    },
    "SILVER : 1 GRAM 999.0 (MYR)": {
      "buy": 6.18,
      "sell": 7.12
    },
    "GOLD OZ": {
      "buy": 4034.96,
      "sell": 4036.95
    },
    "SILVER OZ": {
      "buy": 49.04,
      "sell": 49.25
    },
    "USD/MYR": {
      "buy": 4.1756,
      "sell": 4.1984
    }
  }
}