{
  "updated": 1762498709080,
  "data": {
    "GOLD : 1 KILO 999.9 (MYR)": {
      "buy": 536118,
      "sell": 539461
    },
    "GOLD : 100 GM 999.9 (MYR)": {
      "buy": 53615,
      "sell": 53990
    },
    "GOLD : 50 GM 999.9 (MYR)": {
      "buy": 26808,
      "sell": 27008
    },
    "GOLD : 1 TAEL 999.9 (MYR)": {
      "buy": 20262,
      "sell": 20388
    },
    "SCRAP GOLD IN FINE WEIGHT OF 1KG": {
      "buy": 535448,
      "sell": null
    },
    "SILVER : 1 GRAM 999.0 (MYR)": {
      "buy": 6.11,
      "sell": 7.04
    },
    "GOLD OZ": {
      "buy": 4006.38,
      "sell": 4008.39
    },
    "SILVER OZ": {
      "buy": 48.62,
      "sell": 48.84
    },
    "USD/MYR": {
      "buy": 4.1677,
      "sell": 4.1827
    }
  }
}