{
  "updated": 1764716383781,
  "data": {
    "GOLD : 1 KILO 999.9 (MYR)": {
      "buy": 552656,
      "sell": 563986
    },
    "GOLD : 100 GM 999.9 (MYR)": {
      "buy": 55269,
      "sell": 56442
    },
    "GOLD : 50 GM 999.9 (MYR)": {
      "buy": 27635,
      "sell": 28234
    },
    "GOLD : 1 TAEL 999.9 (MYR)": {
      "buy": 20887,
      "sell": 21315
    },
    "SCRAP GOLD IN FINE WEIGHT OF 1KG": {
      "buy": 551994,
      "sell": null
    },
    "SILVER : 1 GRAM 999.0 (MYR)": {
      "buy": 7.21,
      "sell": 8.21
    },
    "GOLD OZ": {
      "buy": 4181.93,
      "sell": 4230.67
    },
    "SILVER OZ": {
      "buy": 57.47,
      "sell": 58.85
    },
    "USD/MYR": {
      "buy": 4.1157,
      "sell": 4.1433
    }
  }
}