{
  "updated": 1761918100455,
  "data": {
    "GOLD : 1 KILO 999.9 (MYR)": {
      "buy": 538420,
      "sell": 542792
    },
    "GOLD : 100 GM 999.9 (MYR)": {
      "buy": 53845,
      "sell": 54323
    },
    "GOLD : 50 GM 999.9 (MYR)": {
      "buy": 26923,
      "sell": 27175
    },
    "GOLD : 1 TAEL 999.9 (MYR)": {
      "buy": 20349,
      "sell": 20514
    },
    "SCRAP GOLD IN FINE WEIGHT OF 1KG": {
      "buy": 537749,
      "sell": null
    },
    "SILVER : 1 GRAM 999.0 (MYR)": {
      "buy": 6.14,
      "sell": 7.08
    },
    "GOLD OZ": {
      "buy": 4015.96,
      "sell": 4018.07
    },
    "SILVER OZ": {
      "buy": 48.73,
      "sell": 48.95
    },
    "USD/MYR": {
      "buy": 4.1756,
      "sell": 4.1984
    }
  }
}