{
  "updated": 1764769714783,
  "data": {
    "GOLD : 1 KILO 999.9 (MYR)": {
      "buy": 556936,
      "sell": 562057
    },
    "GOLD : 100 GM 999.9 (MYR)": {
      "buy": 55697,
      "sell": 56249
    },
    "GOLD : 50 GM 999.9 (MYR)": {
      "buy": 27849,
      "sell": 28138
    },
    "GOLD : 1 TAEL 999.9 (MYR)": {
      "buy": 21048,
      "sell": 21242
    },
    "SCRAP GOLD IN FINE WEIGHT OF 1KG": {
      "buy": 556276,
      "sell": null
    },
    "SILVER : 1 GRAM 999.0 (MYR)": {
      "buy": 7.35,
      "sell": 8.2
    },
    "GOLD OZ": {
      "buy": 4223.5,
      "sell": 4225.37
    },
    "SILVER OZ": {
      "buy": 58.68,
      "sell": 58.9
    },
    "USD/MYR": {
      "buy": 4.1067,
      "sell": 4.1343
    }
  }
}