{
  "updated": 1764847377661,
  "data": {
    "GOLD : 1 KILO 999.9 (MYR)": {
      "buy": 552601,
      "sell": 557688
    },
    "GOLD : 100 GM 999.9 (MYR)": {
      "buy": 55264,
      "sell": 55812
    },
    "GOLD : 50 GM 999.9 (MYR)": {
      "buy": 27632,
      "sell": 27919
    },
    "GOLD : 1 TAEL 999.9 (MYR)": {
      "buy": 20884,
      "sell": 21077
    },
    "SCRAP GOLD IN FINE WEIGHT OF 1KG": {
      "buy": 551943,
      "sell": null
    },
    "SILVER : 1 GRAM 999.0 (MYR)": {
      "buy": 7.17,
      "sell": 8.02
    },
    "GOLD OZ": {
      "buy": 4199.76,
      "sell": 4201.65
    },
    "SILVER OZ": {
      "buy": 57.43,
      "sell": 57.66
    },
    "USD/MYR": {
      "buy": 4.0978,
      "sell": 4.1253
    }
  }
}