{
  "updated": 1761637438188,
  "data": {
    "GOLD : 1 KILO 999.9 (MYR)": {
      "buy": 528284,
      "sell": 531585
    },
    "GOLD : 100 GM 999.9 (MYR)": {
      "buy": 52832,
      "sell": 53202
    },
    "GOLD : 50 GM 999.9 (MYR)": {
      "buy": 26416,
      "sell": 26615
    },
    "GOLD : 1 TAEL 999.9 (MYR)": {
      "buy": 19965,
      "sell": 20090
    },
    "SCRAP GOLD IN FINE WEIGHT OF 1KG": {
      "buy": 527610,
      "sell": null
    },
    "SILVER : 1 GRAM 999.0 (MYR)": {
      "buy": 5.83,
      "sell": 6.76
    },
    "GOLD OZ": {
      "buy": 3925.52,
      "sell": 3927.45
    },
    "SILVER OZ": {
      "buy": 46.24,
      "sell": 46.47
    },
    "USD/MYR": {
      "buy": 4.1915,
      "sell": 4.2065
    }
  }
}