{
  "updated": 1762494008259,
  "data": {
    "GOLD : 1 KILO 999.9 (MYR)": {
      "buy": 535023,
      "sell": 538375
    },
    "GOLD : 100 GM 999.9 (MYR)": {
      "buy": 53506,
      "sell": 53881
    },
    "GOLD : 50 GM 999.9 (MYR)": {
      "buy": 26753,
      "sell": 26954
    },
    "GOLD : 1 TAEL 999.9 (MYR)": {
      "buy": 20220,
      "sell": 20347
    },
    "SCRAP GOLD IN FINE WEIGHT OF 1KG": {
      "buy": 534353,
      "sell": null
    },
    "SILVER : 1 GRAM 999.0 (MYR)": {
      "buy": 6.08,
      "sell": 7.01
    },
    "GOLD OZ": {
      "buy": 3996.77,
      "sell": 3998.88
    },
    "SILVER OZ": {
      "buy": 48.38,
      "sell": 48.61
    },
    "USD/MYR": {
      "buy": 4.1692,
      "sell": 4.1842
    }
  }
}