{
  "updated": 1763635917336,
  "data": {
    "GOLD : 1 KILO 999.9 (MYR)": {
      "buy": 540619,
      "sell": 545481
    },
    "GOLD : 100 GM 999.9 (MYR)": {
      "buy": 54065,
      "sell": 54592
    },
    "GOLD : 50 GM 999.9 (MYR)": {
      "buy": 27033,
      "sell": 27309
    },
    "GOLD : 1 TAEL 999.9 (MYR)": {
      "buy": 20432,
      "sell": 20615
    },
    "SCRAP GOLD IN FINE WEIGHT OF 1KG": {
      "buy": 539953,
      "sell": null
    },
    "SILVER : 1 GRAM 999.0 (MYR)": {
      "buy": 6.37,
      "sell": 7.31
    },
    "GOLD OZ": {
      "buy": 4062.27,
      "sell": 4064.25
    },
    "SILVER OZ": {
      "buy": 50.77,
      "sell": 51
    },
    "USD/MYR": {
      "buy": 4.1448,
      "sell": 4.1713
    }
  }
}