{
  "updated": 1762861401254,
  "data": {
    "GOLD : 1 KILO 999.9 (MYR)": {
      "buy": 548435,
      "sell": 553357
    },
    "GOLD : 100 GM 999.9 (MYR)": {
      "buy": 54847,
      "sell": 55379
    },
    "GOLD : 50 GM 999.9 (MYR)": {
      "buy": 27423,
      "sell": 27703
    },
    "GOLD : 1 TAEL 999.9 (MYR)": {
      "buy": 20727,
      "sell": 20913
    },
    "SCRAP GOLD IN FINE WEIGHT OF 1KG": {
      "buy": 547773,
      "sell": null
    },
    "SILVER : 1 GRAM 999.0 (MYR)": {
      "buy": 6.37,
      "sell": 7.31
    },
    "GOLD OZ": {
      "buy": 4141.99,
      "sell": 4143.86
    },
    "SILVER OZ": {
      "buy": 51.02,
      "sell": 51.25
    },
    "USD/MYR": {
      "buy": 4.1237,
      "sell": 4.1503
    }
  }
}