{
  "updated": 1763541089705,
  "data": {
    "GOLD : 1 KILO 999.9 (MYR)": {
      "buy": 543117,
      "sell": 546592
    },
    "GOLD : 100 GM 999.9 (MYR)": {
      "buy": 54315,
      "sell": 54703
    },
    "GOLD : 50 GM 999.9 (MYR)": {
      "buy": 27158,
      "sell": 27365
    },
    "GOLD : 1 TAEL 999.9 (MYR)": {
      "buy": 20526,
      "sell": 20657
    },
    "SCRAP GOLD IN FINE WEIGHT OF 1KG": {
      "buy": 542452,
      "sell": null
    },
    "SILVER : 1 GRAM 999.0 (MYR)": {
      "buy": 6.43,
      "sell": 7.35
    },
    "GOLD OZ": {
      "buy": 4086.53,
      "sell": 4088.33
    },
    "SILVER OZ": {
      "buy": 51.29,
      "sell": 51.51
    },
    "USD/MYR": {
      "buy": 4.1392,
      "sell": 4.1552
    }
  }
}